seGMM/__init__.py
seGMM/main.py
seGMM/data/SRY_hg19.bed
seGMM/data/SRY_hg38.bed
seGMM/script/seGMM.r
seGMM-1.3.0.dist-info/METADATA
seGMM-1.3.0.dist-info/WHEEL
seGMM-1.3.0.dist-info/entry_points.txt
seGMM-1.3.0.dist-info/top_level.txt
seGMM-1.3.0.dist-info/RECORD
