Metadata-Version: 2.1
Name: seGMM
Version: 1.3.0
Summary: seGMM is a tool that determines the gender of a sample from the called genotype data integrated BAM files and jointly considers information on the X and Y chromosomes in diverse genotype data including panel data. seGMM apply Gaussian Mixture Model (GMM) clustering to classify the samples into two clusters.
Home-page: https://github.com/liusihan/seGMM
Author: Sihan Liu
Author-email: liusihan@wchscu.cn
Maintainer: Sihan Liu
Maintainer-email: liusihan@wchscu.cn
License: MIT License
Platform: linux
Classifier: Operating System :: OS Independent
Classifier: License :: OSI Approved :: MIT License
Classifier: Programming Language :: Python :: 3
Requires-Python: >=3.7
